{"type":"PR","pr":{"number":160,"head":"6f3bc54890e65889504e6569a9070946aae8cf4b"},"user":"Kento Takano","status":"pending_publish","branch":"cms/2019-07-13-macbook-virtualboxインストールからsshログインまでのセットアップ備忘録-md","collection":"blog","title":"MacBook VirtualBoxインストールからSSHログインまでのセットアップ備忘録","description":"No Description!","objects":{"entry":{"path":"content/2019-07-13-macbook-virtualboxインストールからsshログインまでのセットアップ備忘録-md.md","sha":"0fee699dd0d31c75bfe38b2e0f2a0234ab619d6d"},"files":[]},"timeStamp":"2019-07-13T05:40:53.416Z"}